{"stat.walkOneCm":981626,"stat.leaveGame":1,"achievement.achSmallOre":12,"stat.mineBlock.58":1,"achievement.achSaw":2,"stat.jump":1030,"stat.swimOneCm":8589,"achievement.achCopperAge":33,"stat.fallOneCm":3908,"achievement.achWildVegetable":40,"achievement.buildWorkBench":6,"achievement.achPickaxe":2,"achievement.mineWood":41,"achievement.exploreAllBiomes":{"value":0,"progress":["Mountains","Beach","Gravel Beach","High Plains","High Hills Edge","Ocean","Swamp","River","Rolling Hills","Plains","Mountains Edge"]},"stat.useItem.38":1,"achievement.openInventory":354,"stat.craftItem.5":9,"stat.damageTaken":6350,"achievement.achLooseRock":55,"achievement.achStoneAge":17,"achievement.achTwoKnives":3,"stat.useItem.54":4,"stat.flyOneCm":111360,"stat.craftItem.58":1,"stat.drop":41,"achievement.buildPickaxe":2,"stat.playOneMinute":210077,"achievement.achAnvil":1,"stat.damageDealt":100,"achievement.buildBetterPickaxe":2,"stat.diveOneCm":4290,"stat.useItem.58":2}